semiformal/_tokenizer.cpython-310-i386-linux-gnu.so
semiformal/__init__.py
semiformal/token_types.py
semiformal/tokenizer.py
semiformal-0.7.0.dist-info/RECORD
semiformal-0.7.0.dist-info/WHEEL
semiformal-0.7.0.dist-info/LICENSE
semiformal-0.7.0.dist-info/METADATA
semiformal-0.7.0.dist-info/top_level.txt
